LICENSE
MANIFEST.in
README.rst
pyproject.toml
setup.cfg
setup.py
cleverstack_auth/__init__.py
cleverstack_auth/admin.py
cleverstack_auth/apps.py
cleverstack_auth/backends.py
cleverstack_auth/dbrouter.py
cleverstack_auth/models.py
cleverstack_auth/serializers.py
cleverstack_auth/signals.py
cleverstack_auth/tests.py
cleverstack_auth/tokens.py
cleverstack_auth/urls.py
cleverstack_auth/views.py
cleverstack_auth.egg-info/PKG-INFO
cleverstack_auth.egg-info/SOURCES.txt
cleverstack_auth.egg-info/dependency_links.txt
cleverstack_auth.egg-info/requires.txt
cleverstack_auth.egg-info/top_level.txt
cleverstack_auth/base/__init__.py
cleverstack_auth/base/models.py
cleverstack_auth/base/tokens.py
cleverstack_auth/base/auth/__init__.py
cleverstack_auth/base/auth/authentication.py
cleverstack_auth/base/auth/baseViewSet.py
cleverstack_auth/base/error/__init__.py
cleverstack_auth/base/error/index.py
cleverstack_auth/base/error/response.py
cleverstack_auth/base/error/system.py
cleverstack_auth/base/middleware/__init__.py
cleverstack_auth/base/middleware/custompagination.py
cleverstack_auth/base/middleware/get_company.py
cleverstack_auth/base/middleware/get_user_middleware.py
cleverstack_auth/base/middleware/ranges.py
cleverstack_auth/base/middleware/response.py
cleverstack_auth/management/__init__.py
cleverstack_auth/management/commands/__init__.py
cleverstack_auth/management/commands/create_default_values.py
cleverstack_auth/management/commands/makesuper.py
cleverstack_auth/migrations/0001_initial.py
cleverstack_auth/migrations/0002_alter_user_managers.py
cleverstack_auth/migrations/0003_alter_organisation_options.py
cleverstack_auth/migrations/__init__.py
cleverstack_auth/organisation/__init__.py
cleverstack_auth/organisation/admin.py
cleverstack_auth/organisation/apps.py
cleverstack_auth/organisation/models.py
cleverstack_auth/organisation/serializers.py
cleverstack_auth/organisation/signals.py
cleverstack_auth/organisation/tests.py
cleverstack_auth/organisation/urls.py
cleverstack_auth/organisation/views.py
cleverstack_auth/storage/__init__.py
cleverstack_auth/storage/aws.py
cleverstack_auth/storage/storage_backends.py
cleverstack_auth/utils/__init__.py
