Metadata-Version: 2.1
Name: cleverstack-auth
Version: 0.4.9
Summary: Django based cleverstack auth service for user related operations
Home-page: http://cleverstack-auth.ap-south-1.elasticbeanstalk.com/
Author: Nasir Hussain
Author-email: nasir@technodreams.in
License: BSD-3-Clause
Classifier: Environment :: Web Environment
Classifier: Framework :: Django :: 4.1
Classifier: Intended Audience :: Developers
Classifier: License :: OSI Approved :: BSD License
Classifier: Operating System :: OS Independent
Classifier: Programming Language :: Python
Classifier: Programming Language :: Python :: 3
Classifier: Programming Language :: Python :: 3 :: Only
Classifier: Programming Language :: Python :: 3.6
Classifier: Programming Language :: Python :: 3.7
Classifier: Programming Language :: Python :: 3.8
Classifier: Topic :: Internet :: WWW/HTTP
Classifier: Topic :: Internet :: WWW/HTTP :: Dynamic Content
Requires-Python: >=3.8
License-File: LICENSE
